tag2network/RunWOSExample.py
tag2network/__init__.py
tag2network/runPlotExample.py
tag2network/Network/BuildNetwork.py
tag2network/Network/ClusterLayout.py
tag2network/Network/ClusteringProperties.py
tag2network/Network/DrawNetwork.py
tag2network/Network/InteractiveNetworkViz.py
tag2network/Network/UMAPLayout.py
tag2network/Network/__init__.py
tag2network/Network/louvain.py
tag2network/Network/tSNELayout.py
tag2network/Tags/BuildKeywords.py
tag2network/Tags/__init__.py
tag2network/WOSTags/MergeWOSFiles.py
tag2network/WOSTags/ProcessReferences.py
tag2network/WOSTags/__init__.py
tag2network-0.0.8.dist-info/LICENSE
tag2network-0.0.8.dist-info/METADATA
tag2network-0.0.8.dist-info/WHEEL
tag2network-0.0.8.dist-info/top_level.txt
tag2network-0.0.8.dist-info/RECORD
