Metadata-Version: 2.1
Name: tag2network
Version: 0.0.8
Summary: Build similarity network from tagged documents
Home-page: https://github.com/foodwebster/tag2network
Author: foodwebster
Author-email: foodwebster@gmail.com
License: MIT
Platform: UNKNOWN
Requires-Dist: numpy
Requires-Dist: scipy
Requires-Dist: pandas
Requires-Dist: networkx
